slpkg/__init__.py
slpkg/blacklist.py
slpkg/changelog.py
slpkg/check_updates.py
slpkg/checksum.py
slpkg/choose_dependencies.py
slpkg/choose_packages.py
slpkg/cleanings.py
slpkg/config.py
slpkg/config_editor.py
slpkg/dependees.py
slpkg/dependency_logger.py
slpkg/dialog_box.py
slpkg/download_only.py
slpkg/downloader.py
slpkg/errors.py
slpkg/file_search.py
slpkg/gpg_verify.py
slpkg/install_data.py
slpkg/list_installed.py
slpkg/load_data.py
slpkg/main.py
slpkg/multi_process.py
slpkg/new_configs.py
slpkg/package_validator.py
slpkg/progress_bar.py
slpkg/remove_packages.py
slpkg/repo_info.py
slpkg/repositories.py
slpkg/search.py
slpkg/self_check.py
slpkg/terminal_selector.py
slpkg/toml_errors.py
slpkg/tracking.py
slpkg/update_repositories.py
slpkg/upgrade.py
slpkg/utilities.py
slpkg/binaries/__init__.py
slpkg/binaries/install.py
slpkg/binaries/required.py
slpkg/sbos/__init__.py
slpkg/sbos/dependencies.py
slpkg/sbos/sbo_generate.py
slpkg/sbos/slackbuild.py
slpkg/views/__init__.py
slpkg/views/imprint.py
slpkg/views/info_package.py
slpkg/views/version.py
slpkg/views/view_process.py
slpkg/views/views.py
slpkg-5.5.1.dist-info/entry_points.txt
slpkg-5.5.1.dist-info/licenses/LICENSE
slpkg-5.5.1.dist-info/WHEEL
slpkg-5.5.1.dist-info/METADATA
slpkg-5.5.1.dist-info/RECORD
