Metadata-Version: 2.4
Name: slpkg
Version: 5.5.1
Summary: Package manager utility for Slackware Linux
Keywords: slackware,linux,package,manager,tool
Author-email: Dimitris Zlatanidis <dslackw@gmail.com>
Maintainer-email: Dimitris Zlatanidis <dslackw@gmail.com>
Requires-Python: >=3.9
Classifier: License :: OSI Approved :: GNU General Public License v3 (GPLv3)
Classifier: Natural Language :: English
Classifier: Environment :: Console
Classifier: Operating System :: POSIX
Classifier: Operating System :: POSIX :: Linux
Classifier: Programming Language :: Python
Classifier: Programming Language :: Python :: 3
Classifier: Programming Language :: Unix Shell
Classifier: Topic :: Utilities
Classifier: Topic :: Software Development :: Build Tools
Classifier: Topic :: System :: Archiving :: Packaging
Classifier: Topic :: System :: Software Distribution
Classifier: Topic :: System :: Installation/Setup
Classifier: Topic :: System :: Systems Administration
Classifier: Topic :: System :: Software Distribution
Classifier: Development Status :: 5 - Production/Stable
License-File: LICENSE
Requires-Dist: tomlkit>=0.13.2
Requires-Dist: pythondialog>=3.5.3 ; extra == "dialog"
Requires-Dist: PySocks>=1.7.1 ; extra == "socks"
Project-URL: Changelog, https://gitlab.com/dslackw/slpkg/-/blob/master/CHANGELOG.md
Project-URL: Documentation, https://dslackw.gitlab.io/slpkg/
Project-URL: Homepage, https://dslackw.gitlab.io/slpkg/
Project-URL: Repository, https://gitlab.com/dslackw/slpkg.git
Provides-Extra: dialog
Provides-Extra: socks
